registream/__init__.py
registream/autolabel.py
registream/label_fetcher.py
registream/lookup.py
registream-1.0.1.dist-info/METADATA
registream-1.0.1.dist-info/WHEEL
registream-1.0.1.dist-info/top_level.txt
registream-1.0.1.dist-info/RECORD
