Metadata-Version: 2.4
Name: registream
Version: 1.0.1
Summary: Streamline your registry data workflow
Home-page: https://registream.org
Author: Jeffrey Clark, Jie Wen
License: BSD-3-Clause
Project-URL: Homepage, https://registream.org
Project-URL: Repository, https://github.com/jeffrey-clark/registream
Classifier: Development Status :: 4 - Beta
Classifier: Intended Audience :: Science/Research
Classifier: License :: OSI Approved :: BSD License
Classifier: Programming Language :: Python :: 3
Classifier: Programming Language :: Python :: 3.7
Classifier: Programming Language :: Python :: 3.8
Classifier: Programming Language :: Python :: 3.9
Classifier: Programming Language :: Python :: 3.10
Classifier: Programming Language :: Python :: 3.11
Requires-Python: >=3.7
Requires-Dist: pandas>=1.0.0
Requires-Dist: tqdm>=4.0.0
Requires-Dist: requests>=2.0.0
Requires-Dist: matplotlib>=3.0.0
Requires-Dist: seaborn>=0.11.0
Dynamic: home-page
Dynamic: requires-python
